discovery/__init__.py
discovery/client.py
discovery/types.py
leap_discovery_client-0.1.0.dist-info/METADATA
leap_discovery_client-0.1.0.dist-info/WHEEL
leap_discovery_client-0.1.0.dist-info/RECORD
