Metadata-Version: 2.4
Name: leap-discovery-client
Version: 0.1.0
Summary: Python SDK for the Discovery Engine API
Project-URL: Homepage, https://github.com/leap-laboratories/discovery
Project-URL: Documentation, https://github.com/leap-laboratories/discovery
Project-URL: Repository, https://github.com/leap-laboratories/discovery
Author: Leap Laboratories
License: MIT
Keywords: api,data-analysis,discovery,machine-learning,sdk
Classifier: Development Status :: 4 - Beta
Classifier: Intended Audience :: Developers
Classifier: License :: OSI Approved :: MIT License
Classifier: Programming Language :: Python :: 3
Classifier: Programming Language :: Python :: 3.10
Classifier: Programming Language :: Python :: 3.11
Classifier: Programming Language :: Python :: 3.12
Classifier: Topic :: Scientific/Engineering :: Artificial Intelligence
Classifier: Topic :: Software Development :: Libraries :: Python Modules
Requires-Python: >=3.10
Requires-Dist: httpx>=0.24.0
Requires-Dist: pydantic>=2.0.0
Provides-Extra: dev
Requires-Dist: pytest-asyncio>=0.21.0; extra == 'dev'
Requires-Dist: pytest>=7.0.0; extra == 'dev'
Provides-Extra: pandas
Requires-Dist: pandas>=2.0.0; extra == 'pandas'
